__init__.py
random_number_list.py
random_number_list-0.0.1.dist-info/LICENCE
random_number_list-0.0.1.dist-info/METADATA
random_number_list-0.0.1.dist-info/WHEEL
random_number_list-0.0.1.dist-info/top_level.txt
random_number_list-0.0.1.dist-info/RECORD
