Metadata-Version: 2.1
Name: random-number-list
Version: 0.0.1
Summary: To return a list of randomly drawn numbers from a user defined list of numbers.
Classifier: Programming Language :: Python :: 3
Classifier: Programming Language :: Python :: 3.10
Classifier: License :: OSI Approved :: GNU General Public License v3 or later (GPLv3+)
Classifier: Operating System :: OS Independent
Classifier: Development Status :: 4 - Beta
Classifier: Natural Language :: English
Classifier: Topic :: Utilities
License-File: LICENCE
